{
  "openapi": "3.0.0",
  "info": {
    "title": "api",
    "version": "1.0"
  },
  "servers": [
    {
      "url": "http://localhost:3000/api/v1"
    },
    {
      "url": "http://dev.freks.jp:3000/api/v1",
      "description": "freks"
    }
  ],
  "paths": {
    "/todos": {
      "get": {
        "summary": "",
        "tags": [
          "todo"
        ],
        "responses": {
          "200": {
            "description": "OK",
            "content": {
              "application/json": {
                "schema": {
                  "type": "object",
                  "properties": {
                    "data": {
                      "type": "array",
                      "items": {
                        "required": [
                          "id",
                          "type",
                          "attributes"
                        ],
                        "properties": {
                          "id": {
                            "type": "string"
                          },
                          "type": {
                            "type": "string"
                          },
                          "attributes": {
                            "$ref": "#/components/schemas/todo"
                          }
                        },
                        "type": "object"
                      }
                    }
                  },
                  "required": [
                    "data"
                  ]
                },
                "examples": {
                  "three todos": {
                    "value": {
                      "data": [
                        {
                          "id": "1",
                          "type": "todo",
                          "attributes": {
                            "title": "buy milk",
                            "detail": "at supermarket",
                            "done": false
                          }
                        },
                        {
                          "id": "2",
                          "type": "todo",
                          "attributes": {
                            "title": "clean my room ",
                            "detail": "",
                            "done": false
                          }
                        },
                        {
                          "id": "3",
                          "type": "todo",
                          "attributes": {
                            "title": "go to gym",
                            "detail": "kick-box",
                            "done": true
                          }
                        }
                      ]
                    }
                  }
                }
              }
            }
          }
        },
        "operationId": "get-todos",
        "security": [
          {
            "jwt": []
          }
        ]
      },
      "parameters": [],
      "post": {
        "summary": "",
        "responses": {
          "201": {
            "description": "Created",
            "content": {
              "application/json": {
                "schema": {
                  "type": "object",
                  "properties": {
                    "data": {
                      "properties": {
                        "id": {
                          "type": "string"
                        },
                        "type": {
                          "type": "string"
                        },
                        "attributes": {
                          "$ref": "#/components/schemas/todo"
                        }
                      },
                      "required": [
                        "id",
                        "type",
                        "attributes"
                      ],
                      "type": "object"
                    }
                  },
                  "required": [
                    "data"
                  ]
                },
                "examples": {
                  "one": {
                    "value": {
                      "data": {
                        "id": "1",
                        "type": "todo",
                        "attributes": {
                          "title": "sample title",
                          "detail": "sample detail",
                          "done": false
                        }
                      }
                    }
                  }
                }
              }
            }
          },
          "422": {
            "description": "Unprocessable Entity",
            "content": {
              "application/json": {
                "schema": {
                  "$ref": "#/components/schemas/errors"
                }
              }
            }
          }
        },
        "requestBody": {
          "content": {
            "application/json": {
              "schema": {
                "type": "object",
                "properties": {
                  "todo": {
                    "$ref": "#/components/schemas/todo"
                  }
                },
                "required": [
                  "todo"
                ]
              }
            }
          }
        },
        "security": [
          {
            "jwt": []
          }
        ],
        "tags": [
          "todo"
        ]
      }
    },
    "/todos/{id}": {
      "get": {
        "summary": "",
        "tags": [
          "todo"
        ],
        "responses": {
          "200": {
            "description": "OK",
            "content": {
              "application/json": {
                "schema": {
                  "type": "object",
                  "properties": {
                    "data": {
                      "properties": {
                        "id": {
                          "type": "string"
                        },
                        "type": {
                          "type": "string"
                        },
                        "attributes": {
                          "$ref": "#/components/schemas/todo"
                        }
                      },
                      "required": [
                        "id",
                        "type",
                        "attributes"
                      ],
                      "type": "object"
                    }
                  },
                  "required": [
                    "data"
                  ]
                }
              }
            }
          },
          "": {
            "content": {
              "application/json": {
                "schema": {
                  "type": "object",
                  "properties": {
                    "data": {
                      "items": {
                        "type": "object",
                        "properties": {
                          "id": {
                            "type": "string"
                          },
                          "type": {
                            "type": "string"
                          },
                          "attributes": {
                            "$ref": "#/components/schemas/todo"
                          }
                        },
                        "required": [
                          "id",
                          "type",
                          "attributes"
                        ]
                      },
                      "type": "array"
                    }
                  },
                  "required": [
                    "data"
                  ]
                },
                "examples": {
                  "one": {
                    "value": {
                      "data": {
                        "id": "1",
                        "type": "todo",
                        "attributes": {
                          "title": "buy milk",
                          "detail": "at supermarket",
                          "done": false
                        }
                      }
                    }
                  }
                }
              }
            }
          }
        },
        "parameters": [],
        "description": "",
        "requestBody": {},
        "security": [
          {
            "jwt": []
          }
        ]
      },
      "parameters": [
        {
          "schema": {
            "type": "string"
          },
          "name": "id",
          "in": "path",
          "required": true
        }
      ],
      "put": {
        "summary": "",
        "responses": {
          "200": {
            "description": "OK",
            "content": {
              "application/json": {
                "schema": {
                  "type": "object",
                  "properties": {
                    "data": {
                      "properties": {
                        "id": {
                          "type": "string"
                        },
                        "type": {
                          "type": "string"
                        },
                        "attributes": {
                          "$ref": "#/components/schemas/todo"
                        }
                      },
                      "required": [
                        "id",
                        "type",
                        "attributes"
                      ],
                      "type": "object"
                    }
                  },
                  "required": [
                    "data"
                  ]
                }
              }
            }
          },
          "422": {
            "description": "Unprocessable Entity",
            "content": {
              "application/json": {
                "schema": {
                  "$ref": "#/components/schemas/errors"
                }
              }
            }
          }
        },
        "requestBody": {
          "content": {
            "application/json": {
              "schema": {
                "type": "object",
                "properties": {
                  "data": {
                    "$ref": "#/components/schemas/todo"
                  }
                },
                "required": [
                  "data"
                ]
              }
            }
          },
          "description": ""
        },
        "security": [
          {
            "jwt": []
          }
        ],
        "tags": [
          "todo"
        ]
      },
      "delete": {
        "summary": "",
        "responses": {
          "204": {
            "description": "No Content"
          }
        },
        "security": [
          {
            "jwt": []
          }
        ],
        "tags": [
          "todo"
        ]
      }
    },
    "/users": {
      "get": {
        "summary": "",
        "tags": [
          "user"
        ],
        "responses": {
          "200": {
            "description": "OK",
            "content": {
              "application/json": {
                "schema": {
                  "type": "object",
                  "properties": {
                    "data": {
                      "type": "array",
                      "items": {
                        "type": "object",
                        "properties": {
                          "id": {
                            "type": "string"
                          },
                          "type": {
                            "type": "string"
                          },
                          "attributes": {
                            "$ref": "#/components/schemas/user"
                          }
                        },
                        "required": [
                          "id",
                          "type",
                          "attributes"
                        ]
                      }
                    }
                  },
                  "required": [
                    "data"
                  ]
                }
              }
            }
          }
        },
        "operationId": "get-users",
        "security": [
          {
            "jwt": []
          }
        ]
      },
      "post": {
        "summary": "",
        "operationId": "post-users",
        "responses": {
          "201": {
            "description": "Created",
            "content": {
              "application/json": {
                "schema": {
                  "type": "object",
                  "properties": {
                    "data": {
                      "type": "object",
                      "required": [
                        "id",
                        "type",
                        "attributes"
                      ],
                      "properties": {
                        "id": {
                          "type": "string"
                        },
                        "type": {
                          "type": "string"
                        },
                        "attributes": {
                          "$ref": "#/components/schemas/user"
                        }
                      }
                    }
                  },
                  "required": [
                    "data"
                  ]
                }
              }
            }
          },
          "422": {
            "description": "Unprocessable Entity",
            "content": {
              "application/json": {
                "schema": {
                  "$ref": "#/components/schemas/errors"
                }
              }
            }
          }
        },
        "requestBody": {
          "content": {
            "application/json": {
              "schema": {
                "type": "object",
                "properties": {
                  "user": {
                    "$ref": "#/components/schemas/user"
                  }
                }
              }
            }
          }
        },
        "tags": [
          "user"
        ]
      }
    },
    "/users/{id}": {
      "get": {
        "summary": "",
        "tags": [
          "user"
        ],
        "responses": {
          "200": {
            "description": "OK",
            "content": {
              "application/json": {
                "schema": {
                  "type": "object",
                  "properties": {
                    "data": {
                      "required": [
                        "id",
                        "type",
                        "attributes"
                      ],
                      "type": "object",
                      "properties": {
                        "id": {
                          "type": "string"
                        },
                        "type": {
                          "type": "string"
                        },
                        "attributes": {
                          "$ref": "#/components/schemas/user"
                        }
                      }
                    }
                  },
                  "required": [
                    "data"
                  ]
                }
              }
            }
          }
        },
        "operationId": "get-users-(id)",
        "security": [
          {
            "jwt": []
          }
        ]
      },
      "parameters": [
        {
          "schema": {
            "type": "string"
          },
          "name": "id",
          "in": "path",
          "required": true
        }
      ],
      "put": {
        "summary": "",
        "operationId": "put-users-{id}",
        "responses": {
          "200": {
            "description": "OK",
            "content": {
              "application/json": {
                "schema": {
                  "type": "object",
                  "properties": {
                    "data": {
                      "required": [
                        "id",
                        "type",
                        "attributes"
                      ],
                      "type": "object",
                      "properties": {
                        "id": {
                          "type": "string"
                        },
                        "type": {
                          "type": "string"
                        },
                        "attributes": {
                          "$ref": "#/components/schemas/user"
                        }
                      }
                    }
                  },
                  "required": [
                    "data"
                  ]
                }
              }
            }
          },
          "422": {
            "description": "Unprocessable Entity",
            "content": {
              "application/json": {
                "schema": {
                  "$ref": "#/components/schemas/errors"
                }
              }
            }
          }
        },
        "requestBody": {
          "content": {
            "application/json": {
              "schema": {
                "type": "object",
                "properties": {
                  "user": {
                    "$ref": "#/components/schemas/user"
                  }
                },
                "required": [
                  "user"
                ]
              }
            }
          }
        },
        "security": [
          {
            "jwt": []
          }
        ],
        "tags": [
          "user"
        ]
      },
      "delete": {
        "summary": "",
        "operationId": "delete-users-{id}",
        "responses": {
          "204": {
            "description": "No Content"
          }
        },
        "security": [
          {
            "jwt": []
          }
        ],
        "tags": [
          "user"
        ]
      }
    },
    "/sign_in": {
      "post": {
        "summary": "Sign in",
        "tags": [],
        "responses": {
          "201": {
            "description": "OK",
            "content": {
              "application/json": {
                "schema": {
                  "type": "object",
                  "properties": {
                    "jwt": {
                      "type": "string"
                    }
                  },
                  "required": [
                    "jwt"
                  ]
                }
              }
            }
          }
        },
        "operationId": "post-sign_in",
        "requestBody": {
          "content": {
            "application/json": {
              "schema": {
                "type": "object",
                "properties": {
                  "auth": {
                    "type": "object",
                    "required": [
                      "email",
                      "password"
                    ],
                    "properties": {
                      "email": {
                        "type": "string"
                      },
                      "password": {
                        "type": "string"
                      }
                    }
                  }
                },
                "required": [
                  "auth"
                ]
              }
            }
          }
        },
        "description": ""
      }
    }
  },
  "components": {
    "schemas": {
      "todo": {
        "title": "todo",
        "type": "object",
        "x-tags": [
          "todo"
        ],
        "x-examples": {
          "one": {
            "data": [
              {
                "id": "1",
                "type": "todo",
                "attributes": {
                  "title": "buy milk",
                  "detail": "at supermarket",
                  "done": false
                }
              }
            ]
          }
        },
        "description": "",
        "properties": {
          "title": {
            "type": "string"
          },
          "detail": {
            "type": "string"
          },
          "done": {
            "type": "boolean"
          }
        },
        "required": [
          "title",
          "detail",
          "done"
        ]
      },
      "errors": {
        "title": "errors",
        "type": "object",
        "properties": {
          "errors": {
            "type": "array",
            "items": {
              "type": "object"
            }
          }
        },
        "required": [
          "errors"
        ]
      },
      "user": {
        "title": "user",
        "type": "object",
        "x-tags": [
          "user"
        ],
        "properties": {
          "email": {
            "type": "string"
          },
          "name": {
            "type": "string"
          },
          "password": {
            "type": "string"
          },
          "password_confirmation": {
            "type": "string"
          }
        },
        "required": [
          "email",
          "name"
        ]
      }
    },
    "securitySchemes": {
      "jwt": {
        "name": "Authentication",
        "type": "apiKey",
        "in": "header"
      }
    }
  }
}
